MANIFEST.in
README.rst
setup.py
docs/conf.py
docs/index.rst
xbob/__init__.py
xbob.db.faceverif_fl.egg-info/PKG-INFO
xbob.db.faceverif_fl.egg-info/SOURCES.txt
xbob.db.faceverif_fl.egg-info/dependency_links.txt
xbob.db.faceverif_fl.egg-info/entry_points.txt
xbob.db.faceverif_fl.egg-info/namespace_packages.txt
xbob.db.faceverif_fl.egg-info/not-zip-safe
xbob.db.faceverif_fl.egg-info/requires.txt
xbob.db.faceverif_fl.egg-info/top_level.txt
xbob/db/__init__.py
xbob/db/faceverif_fl/__init__.py
xbob/db/faceverif_fl/driver.py
xbob/db/faceverif_fl/models.py
xbob/db/faceverif_fl/query.py
xbob/db/faceverif_fl/test.py
xbob/db/faceverif_fl/example_fl/dev/for_models.lst
xbob/db/faceverif_fl/example_fl/dev/for_probes.lst
xbob/db/faceverif_fl/example_fl/dev/for_scores.lst
xbob/db/faceverif_fl/example_fl/dev/for_tnorm.lst
xbob/db/faceverif_fl/example_fl/dev/for_znorm.lst
xbob/db/faceverif_fl/example_fl/eval/for_models.lst
xbob/db/faceverif_fl/example_fl/eval/for_probes.lst
xbob/db/faceverif_fl/example_fl/eval/for_scores.lst
xbob/db/faceverif_fl/example_fl/eval/for_tnorm.lst
xbob/db/faceverif_fl/example_fl/eval/for_znorm.lst
xbob/db/faceverif_fl/example_fl/norm/train_world.lst