Metadata-Version: 1.1
Name: xbob.db.faceverif-fl
Version: 1.1.0
Summary: Face Verification File List Database Access API for Bob
Home-page: http://github.com/bioidiap/bob.db.faceverif_fl
Author: Laurent El Shafey
Author-email: laurent.el-shafey@idiap.ch
License: GPLv3
Platform: UNKNOWN
Classifier: Development Status :: 4 - Beta
Classifier: Intended Audience :: Developers
Classifier: License :: OSI Approved :: GNU General Public License v3 (GPLv3)
Classifier: Natural Language :: English
Classifier: Programming Language :: Python
Classifier: Topic :: Scientific/Engineering :: Artificial Intelligence
Classifier: Topic :: Database :: Front-Ends
